{
    "loginButton": "Iniciar sesion",
    "loginText": "¿No tienes una cuenta? Toca aqui para crear una",
    "resetPasswordText": "Restablecer contraseña",
    "emailLabel": "Email",
    "passwordLabel": "Contraseña",
    "registerButton": "Registrar",
    "registerText": "¿Ya tienes una cuenta? Toca aqui para iniciar sesion",
    "nameLabel": "Nombre",
    "surnameLabel": "Apellidos",
    "usernameLabel": "Nombre de usuario",
    "passwordFormatErrorText": "La contraseña debe de tener minimo 8 caracteres e incluir una letra mayuscula y minuscula y un numero.",
    "allFieldsRequiredText": "Todos los campos son obligatorios",
    "emailVerificationText": "Verificando email...",
    "resendButtonText": "Volver a enviar",
    "numCompetitionsSavedLabel": "Competiciones guardadas",
    "numTeamsSavedLabel": "Equipos guardados",
    "numPlayersSavedLabel": "Jugadores guardados",
    "cropImageAppBarTitle": "Ajustar la imagen",
    "homeScreenTitle": "Liga Master",
    "competitionsLabel": "Competiciones",
    "teamsLabel": "Equipos",
    "playersLabel": "Jugadores",
    "deleteItemDialogTitle": "Atencion",
    "deleteCompetitionText": "¿Eliminar la competicion?",
    "addCompetitionText": "Crear competicion",
    "addCompetitionByCodeText": "Añadir competicion de otro usuario",
    "successMessage": "Competicion añadida con exito",
    "errorMessage": "Competicion no encontrada",
    "insertCodeLabel": "Insertar codigo",
    "addCompetitionByCodeLabel": "Añadir competicion",
    "acceptDialogButtonText": "Aceptar",
    "addCompetitionScreenTitle": "Crear competicion",
    "sportLabel": "Deporte",
    "numberOfTeamsThatParticipateLabel": "Numero de equipos",
    "formatLabel": "Formato",
    "selectTeamsButtonText": "Seleccionar equipos",
    "cancelTextButton": "Cancelar",
    "noTeamsAvaliableToAddText": "No tienes equipos de ese deporte o el numero de jugadores de estos es insuficiente",
    "errorNumberOfTeamsSelected": "La cantidad de equipos que has seleccionado no coincide con el indicado anteriormente",
    "infoTabLabel": "Informacion",
    "teamsTabLabel": "Equipos",
    "rankingTabLabel": "Clasificacion",
    "resultsTabLabel": "Resultados",
    "fixturesTabLabel": "Calendario",
    "statsTabLabel": "Estadisticas",
    "creatorLabel": "Creador",
    "codeLabel": "Codigo",
    "matchesLabel": "Partidos",
    "goalsScoredLabel": "Goles",
    "goalsConcededLabel": "Goles recibidos",
    "assistsLabel": "Asistencias",
    "yellowCardsLabel": "Tarjetas amarillas",
    "redCardsLabel": "Tarjetas rojas",
    "statusLabel": "Estado",
    "playersTitle": "Jugadores",
    "teamLabel": "Equipo",
    "pointsLabel": "Pts",
    "victoriesLabel": "V",
    "losesLabel": "P",
    "tiesLabel": "E",
    "goalDifferenceLabel": "DG",
    "roundLabel": "Ronda",
    "noRoundsMessage": "No hay rondas para mostrar",
    "noFixturesMessage": "No hay jornadas creadas",
    "generateNextRoundButtonText": "Generar siguiente ronda",
    "resetTournamentButtonText": "Reiniciar torneo",
    "generateFixturesText": "Crear jornadas",
    "numberOfTimesTeamsFaceEachOtherText": "Numero de veces que cada equipo juega contra el resto",
    "createFixtureButtonText": "Crear",
    "matchDetailsTitle": "Detalles del partido",
    "selectEventTitle": "Selecciona un evento",
    "selectTeamTitle": "Selecciona un equipo",
    "selectPlayerTitle": "Selecciona un jugador",
    "banLengthTitle": "Duración de la suspensión",
    "banLengthErrorMessage": "La duración de la suspensión debe de ser entre uno y el numero de jornadas restantes",
    "saveMatchDialogText": "¿Guardar el partido? NO podrás añadirle eventos de nuevo. Si quieres cambiar la fecha o la ubicacion, pulsa el icono de la flecha y se guardará.",
    "dateErrorText": "Selecciona una fecha valida",
    "timeErrorText": "Selecciona una hora valida",
    "deleteTeamText": "¿Eliminar el equipo?",
    "editTeamTitle": "Editar equipo",
    "playersInTeamTitle": "Jugadores en el equipo",
    "closeDialogText": "Cerrar",
    "playersButtonText": "Ver jugadores",
    "noPlayersInTeamText": "No hay jugadores en el equipo",
    "noPlayersAvaliableToSelect": "No hay jugadores sin equipo de este deporte. Cree unos nuevos",
    "uniqueNameError": "El nombre debe de ser unico",
    "addTeamTitle": "Crear equipo",
    "ratingLabel": "Valoracion",
    "deletePlayerText": "¿Eliminar el jugador?",
    "noTeamText": "Sin equipo",
    "editPlayerTitle": "Editar jugador",
    "positionLabel": "Posicion",
    "createPlayerTitle": "Crear jugador"
}